README.md
setup.cfg
setup.py
pytcher/__init__.py
pytcher/_version.py
pytcher/app.py
pytcher/defaults.py
pytcher/matchers.py
pytcher/request.py
pytcher/watcher.py
pytcher.egg-info/PKG-INFO
pytcher.egg-info/SOURCES.txt
pytcher.egg-info/dependency_links.txt
pytcher.egg-info/requires.txt
pytcher.egg-info/top_level.txt